CMakeLists.txt
LICENSE
MANIFEST.in
README.md
setup.cfg
setup.py
docs/Makefile
docs/make.bat
docs/source/about.rst
docs/source/changelog.rst
docs/source/conda.rst
docs/source/conf.py
docs/source/index.rst
docs/source/module.rst
docs/source/pytide.rst
docs/source/pytide_core.rst
docs/source/pytide_version.rst
docs/source/setup.rst
docs/source/tutorial.rst
src/pytide/__init__.py
src/pytide/core.pyi
src/pytide/version.py
src/pytide.egg-info/PKG-INFO
src/pytide.egg-info/SOURCES.txt
src/pytide.egg-info/dependency_links.txt
src/pytide.egg-info/not-zip-safe
src/pytide.egg-info/requires.txt
src/pytide.egg-info/top_level.txt
src/pytide/core/CMakeLists.txt
src/pytide/core/angle.hpp
src/pytide/core/astronomic_angle.cpp
src/pytide/core/astronomic_angle.hpp
src/pytide/core/main.cpp
src/pytide/core/math.hpp
src/pytide/core/wave.cpp
src/pytide/core/wave.hpp
src/scripts/mit_gcm_detiding.py
tests/__init__.py
tests/test_core.py
tests/test_pytide.py
tests/dataset/fes_tide_time_series.nc
third_party/pybind11/.appveyor.yml
third_party/pybind11/.clang-format
third_party/pybind11/.clang-tidy
third_party/pybind11/.cmake-format.yaml
third_party/pybind11/.codespell-ignore-lines
third_party/pybind11/.git
third_party/pybind11/.gitattributes
third_party/pybind11/.gitignore
third_party/pybind11/.pre-commit-config.yaml
third_party/pybind11/.readthedocs.yml
third_party/pybind11/CMakeLists.txt
third_party/pybind11/LICENSE
third_party/pybind11/MANIFEST.in
third_party/pybind11/README.rst
third_party/pybind11/SECURITY.md
third_party/pybind11/noxfile.py
third_party/pybind11/pyproject.toml
third_party/pybind11/setup.cfg
third_party/pybind11/setup.py
third_party/pybind11/.github/CODEOWNERS
third_party/pybind11/.github/CONTRIBUTING.md
third_party/pybind11/.github/dependabot.yml
third_party/pybind11/.github/labeler.yml
third_party/pybind11/.github/labeler_merged.yml
third_party/pybind11/.github/pull_request_template.md
third_party/pybind11/.github/ISSUE_TEMPLATE/bug-report.yml
third_party/pybind11/.github/ISSUE_TEMPLATE/config.yml
third_party/pybind11/.github/matchers/pylint.json
third_party/pybind11/.github/workflows/ci.yml
third_party/pybind11/.github/workflows/configure.yml
